heinsight/__init__.py
heinsight/heinsight.py
heinsight/heinsight_api.py
heinsight/stream.py
heinsight/utils.py
heinsight/models/__init__.py
heinsight/models/best_content.pt
heinsight/models/best_vessel.pt
heinsight-0.4.4.dist-info/licenses/LICENSE
heinsight-0.4.4.dist-info/METADATA
heinsight-0.4.4.dist-info/WHEEL
heinsight-0.4.4.dist-info/entry_points.txt
heinsight-0.4.4.dist-info/top_level.txt
heinsight-0.4.4.dist-info/RECORD
