Metadata-Version: 2.4
Name: heinsight
Version: 0.4.4
Summary: A Computer Vision System for Dynamic Monitoring of Chemical Experiments
Requires-Python: >=3.8
License-File: LICENSE
Requires-Dist: requests
Requires-Dist: ultralytics
Requires-Dist: fastapi
Requires-Dist: uvicorn
Provides-Extra: api
Requires-Dist: requests; extra == "api"
Dynamic: license-file
